{"/":{"bundle.e8ca6.css":{"type":"style","weight":1},"bundle.d597a.js":{"type":"script","weight":1},"route-home.chunk.45253.js":{"type":"script","weight":0.9},"route-home.chunk.f0ad8.css":{"type":"style","weight":0.9}},"/.chunk.f0ad8.css":{"bundle.e8ca6.css":{"type":"style","weight":1},"bundle.d597a.js":{"type":"script","weight":1},"route-home.chunk.f0ad8.css":{"type":"script","weight":0.9}},"/2.chunk.f0ad8.css":{"bundle.e8ca6.css":{"type":"style","weight":1},"bundle.d597a.js":{"type":"script","weight":1},"route-home2.chunk.f0ad8.css":{"type":"script","weight":0.9}},"/2":{"bundle.e8ca6.css":{"type":"style","weight":1},"bundle.d597a.js":{"type":"script","weight":1},"route-home2.chunk.6ad7b.js":{"type":"script","weight":0.9},"route-home2.chunk.f0ad8.css":{"type":"style","weight":0.9}}}